multi_indexed_collection.py
multi_indexed_collection-1.1.0.dist-info/DESCRIPTION.rst
multi_indexed_collection-1.1.0.dist-info/METADATA
multi_indexed_collection-1.1.0.dist-info/RECORD
multi_indexed_collection-1.1.0.dist-info/WHEEL
multi_indexed_collection-1.1.0.dist-info/metadata.json
multi_indexed_collection-1.1.0.dist-info/top_level.txt
