Metadata-Version: 2.0
Name: multi-indexed-collection
Version: 1.1.0
Summary: A collection for arbitrary objects, that indexes them based on (a given subset of) their properties.
Home-page: https://github.com/Qqwy/python-multiple_indexed_collection
Author: Qqwy/Wiebe-Marten Wijnja
Author-email: qqwy@gmx.com
License: UNKNOWN
Platform: UNKNOWN
Classifier: Development Status :: 3 - Alpha
Classifier: Intended Audience :: Developers
Requires-Python: >=3
